diggs_trial/__init__.py
diggs_trial/cli.py
diggs_trial/diggs_trial.py
diggs_trial-0.0.5.dist-info/AUTHORS.rst
diggs_trial-0.0.5.dist-info/LICENSE
diggs_trial-0.0.5.dist-info/METADATA
diggs_trial-0.0.5.dist-info/WHEEL
diggs_trial-0.0.5.dist-info/dependency_links.txt
diggs_trial-0.0.5.dist-info/entry_points.txt
diggs_trial-0.0.5.dist-info/top_level.txt
diggs_trial-0.0.5.dist-info/RECORD
