Metadata-Version: 2.1
Name: diggs-trial
Version: 0.0.5
Summary: A trial diggs python package
Home-page: https://github.com/xp-geotech/diggs_trial
Author: Xin Peng
Author-email: xin_peng@outlook.com
License: GNU General Public License v3
Keywords: diggs_trial
Platform: UNKNOWN
Classifier: Development Status :: 2 - Pre-Alpha
Classifier: Intended Audience :: Developers
Classifier: License :: OSI Approved :: GNU General Public License v3 (GPLv3)
Classifier: Natural Language :: English
Classifier: Programming Language :: Python :: 3
Classifier: Programming Language :: Python :: 3.5
Classifier: Programming Language :: Python :: 3.6
Classifier: Programming Language :: Python :: 3.7
Classifier: Programming Language :: Python :: 3.8
Requires-Python: >=3.5
Requires-Dist: jupyter
Requires-Dist: lxml
Requires-Dist: pytest
Requires-Dist: pytest-runner
Requires-Dist: rich
